markov_ai/__init__.py
markov_ai/component.py
markov_ai/constants.py
markov_ai/destination.py
markov_ai/exceptions.py
markov_ai/pipeline.py
markov_ai/retriever.py
markov_ai/service.py
markov_ai/utils.py
markov_ai/components/__init__.py
markov_ai/components/data_loader.py
markov_ai/components/pre_processor.py
markov_ai-0.1.10.dist-info/METADATA
markov_ai-0.1.10.dist-info/WHEEL
markov_ai-0.1.10.dist-info/top_level.txt
markov_ai-0.1.10.dist-info/RECORD
