Metadata-Version: 2.1
Name: markov-ai
Version: 0.1.10
Summary: A Python SDK for interacting with Markov AI
Home-page: https://github.com/markov-ai-xyz/markov-ai-python-sdk
Author: Anant Chandra
Author-email: anantchandra98@gmail.com
Classifier: Programming Language :: Python :: 3
Classifier: License :: OSI Approved :: MIT License
Classifier: Operating System :: OS Independent
Requires-Dist: requests>=2.25.1
Requires-Dist: requests-toolbelt>=1.0.0
